{
	"auth": {
		"amplifytodolistc7ec2f0c": {
			"service": "Cognito",
			"providerPlugin": "awscloudformation",
			"dependsOn": []
		}
	},
	"api": {
		"amplifytodolist": {
			"service": "AppSync",
			"providerPlugin": "awscloudformation",
			"output": {
				"authConfig": {
					"additionalAuthenticationProviders": [],
					"defaultAuthentication": {
						"authenticationType": "AMAZON_COGNITO_USER_POOLS",
						"userPoolConfig": {
							"userPoolId": "authamplifytodolistc7ec2f0c"
						}
					}
				}
			}
		}
	}
}